once/releaser/__init__.py
once/releaser/towncrier.py
once/releaser/utils.py
once/releaser/tests/__init__.py
once_releaser-1.1.dist-info/licenses/LICENSE.GPL
once_releaser-1.1.dist-info/licenses/LICENSE.rst
once_releaser-1.1.dist-info/METADATA
once_releaser-1.1.dist-info/WHEEL
once_releaser-1.1.dist-info/entry_points.txt
once_releaser-1.1.dist-info/top_level.txt
once_releaser-1.1.dist-info/RECORD
