Metadata-Version: 2.4
Name: once.releaser
Version: 1.1
Summary: Custom releaser hooks for ONCE project based on zest.releaser
Author-email: Rafael Bermúdez Horcajada <rber474@gmail.com>
License: GPL
Project-URL: documentation, https://github.com/rber474/once.releaser/
Project-URL: repository, https://github.com/rber474/once.releaser/
Project-URL: changelog, https://github.com/rber474/once.releaser/blob/master/CHANGES.rst
Keywords: releasing,packaging,pypi
Classifier: Development Status :: 6 - Mature
Classifier: Intended Audience :: Developers
Classifier: License :: OSI Approved :: GNU General Public License (GPL)
Classifier: Programming Language :: Python
Classifier: Programming Language :: Python :: 3
Classifier: Programming Language :: Python :: 3 :: Only
Classifier: Programming Language :: Python :: 3.10
Classifier: Programming Language :: Python :: 3.11
Classifier: Programming Language :: Python :: 3.12
Classifier: Programming Language :: Python :: 3.13
Classifier: Programming Language :: Python :: Implementation :: CPython
Classifier: Programming Language :: Python :: Implementation :: PyPy
Classifier: Topic :: Software Development :: Libraries :: Python Modules
Requires-Python: >=3.9
License-File: LICENSE.GPL
License-File: LICENSE.rst
Requires-Dist: zest.releaser[recommended]>=9.6.1
Requires-Dist: zestreleaser.towncrier>=1.3.0
Provides-Extra: test
Requires-Dist: zope.testing; extra == "test"
Requires-Dist: zope.testrunner; extra == "test"
Dynamic: license-file
